Metadata-Version: 1.1
Name: cryptostats
Version: 0.0.4
Summary: A simple api wrapper for the nomics api to get crypto stats
Home-page: UNKNOWN
Author: Niklas Schellong
Author-email: nik.schellong.04@gmx.de
License: MIT
Keywords: crypto
Platform: UNKNOWN
Classifier: Development Status :: 5 - Production/Stable
Classifier: Intended Audience :: Education
Classifier: Operating System :: Microsoft :: Windows :: Windows 10
Classifier: License :: OSI Approved :: MIT License
Classifier: Programming Language :: Python :: 3
